xcom/__init__.py
xcom/__main__.py
xcom/log_config.py
xcom/tools.py
xcom/vector.py
xcom/modbus/__init__.py
xcom/modbus/modbus.py
xcom/modbus/modbus_sepam_opg.py
xcom/modbus/modbus_server.py
xcom/modbus/opg.py
xcom-0.0.2.dist-info/LICENSE
xcom-0.0.2.dist-info/METADATA
xcom-0.0.2.dist-info/WHEEL
xcom-0.0.2.dist-info/top_level.txt
xcom-0.0.2.dist-info/RECORD
