Metadata-Version: 2.1
Name: xcom
Version: 0.0.2
Summary: 
